schemania/__init__.py
schemania/error.py
schemania/formatter.py
schemania/schema.py
schemania/validator.py
schemania-0.1.0.dist-info/METADATA
schemania-0.1.0.dist-info/RECORD
schemania-0.1.0.dist-info/WHEEL
schemania-0.1.0.dist-info/top_level.txt
