Metadata-Version: 2.1
Name: schemania
Version: 0.1.0
Summary: Validate data with schemas and be in control of error messages.
Home-page: https://github.com/jcollado/schemania
Author: Javier Collado
Author-email: javier.collado@gmail.com
License: MIT license
Keywords: schemania
Platform: UNKNOWN
Classifier: Development Status :: 2 - Pre-Alpha
Classifier: Intended Audience :: Developers
Classifier: License :: OSI Approved :: MIT License
Classifier: Natural Language :: English
Classifier: Programming Language :: Python :: 2
Classifier: Programming Language :: Python :: 2.7
Classifier: Programming Language :: Python :: 3
Classifier: Programming Language :: Python :: 3.6
